waldur_site_agent_moab/__init__.py
waldur_site_agent_moab/backend.py
waldur_site_agent_moab/client.py
waldur_site_agent_moab/parser.py
waldur_site_agent_moab-0.8.2.dist-info/METADATA
waldur_site_agent_moab-0.8.2.dist-info/WHEEL
waldur_site_agent_moab-0.8.2.dist-info/entry_points.txt
waldur_site_agent_moab-0.8.2.dist-info/RECORD
